GRID_LRT/Token.py
GRID_LRT/__githash__
GRID_LRT/__init__.py
GRID_LRT/__update_GRID_LRT_date.py
GRID_LRT/get_picas_credentials.py
GRID_LRT/grid_credentials.py
GRID_LRT/sandbox.py
GRID_LRT/token.py
GRID_LRT/Application/__init__.py
GRID_LRT/Application/submit.py
GRID_LRT/Staging/__init__.py
GRID_LRT/Staging/pythonpath.py
GRID_LRT/Staging/srmlist.py
GRID_LRT/Staging/stage_all.py
GRID_LRT/Staging/stage_all_LTA.py
GRID_LRT/Staging/stager_access.py
GRID_LRT/Staging/state_all.py
GRID_LRT/Storage/__init__.py
GRID_LRT/Storage/cleanup.py
GRID_LRT/Storage/gsifile.py
GRID_LRT/Storage/utils.py
GRID_LRT/application/__init__.py
GRID_LRT/application/submit.py
GRID_LRT/auth/__init__.py
GRID_LRT/auth/get_picas_credentials.py
GRID_LRT/auth/grid_credentials.py
GRID_LRT/couchdb/__init__.py
GRID_LRT/couchdb/client.py
GRID_LRT/couchdb/design.py
GRID_LRT/couchdb/http.py
GRID_LRT/couchdb/json.py
GRID_LRT/couchdb/loader.py
GRID_LRT/couchdb/mapping.py
GRID_LRT/couchdb/multipart.py
GRID_LRT/couchdb/util.py
GRID_LRT/couchdb/util2.py
GRID_LRT/couchdb/util3.py
GRID_LRT/couchdb/view.py
GRID_LRT/data/config/NDPPP_parset.cfg
GRID_LRT/data/config/bash_file.cfg
GRID_LRT/data/config/tutorial.cfg
GRID_LRT/data/config/steps/cal_pref3.json
GRID_LRT/data/config/steps/pref_cal1.cfg
GRID_LRT/data/config/steps/pref_cal2.cfg
GRID_LRT/data/config/steps/pref_targ1.cfg
GRID_LRT/data/config/steps/pref_targ2.cfg
GRID_LRT/data/config/steps/targ1_pref3.json
GRID_LRT/data/config/steps/targ2_pref3.json
GRID_LRT/data/launchers/run_remote_sandbox.sh
GRID_LRT/storage/__init__.py
GRID_LRT/storage/cleanup.py
GRID_LRT/storage/gsifile.py
GRID_LRT/storage/utils.py
GRID_LRT-1.0.3.data/data/GRID_LRT/data/config/cal_pref3.json
GRID_LRT-1.0.3.data/data/GRID_LRT/data/config/pref_targ2.cfg
GRID_LRT-1.0.3.data/data/GRID_LRT/data/config/targ1_pref3.json
GRID_LRT-1.0.3.data/data/GRID_LRT/data/config/targ2_pref3.json
GRID_LRT-1.0.3.dist-info/DESCRIPTION.rst
GRID_LRT-1.0.3.dist-info/METADATA
GRID_LRT-1.0.3.dist-info/RECORD
GRID_LRT-1.0.3.dist-info/WHEEL
GRID_LRT-1.0.3.dist-info/metadata.json
GRID_LRT-1.0.3.dist-info/top_level.txt
