Metadata-Version: 1.1
Name: GRID-LRT
Version: 1.0.3
Summary: GRID LOFAR Reduction Tools
Home-page: https://www.github.com/apmechev/GRID_LRT/
Author: Alexandar Mechev
Author-email: apmechev+LOFAR@gmail.com
License: UNKNOWN
Download-URL: https://github.com/apmechev/GRID_LRT/archive/v1.0.3.tar.gz
Keywords: surfsara,distributed-computing,LOFAR
Platform: UNKNOWN
Classifier: Development Status :: 5 - Production/Stable
Classifier: Intended Audience :: Developers
Classifier: Intended Audience :: Science/Research
Classifier: License :: OSI Approved :: GNU General Public License v3 (GPLv3)
Classifier: Natural Language :: English
Classifier: Topic :: Scientific/Engineering :: Astronomy
Classifier: Topic :: System :: Distributed Computing
Classifier: Programming Language :: Python :: 2.7
Classifier: Programming Language :: Python :: 3.3
Classifier: Programming Language :: Python :: 3.4
Classifier: Programming Language :: Python :: 3.5
Classifier: Programming Language :: Python :: 3.6
